entelequia/__init__.py
entelequia/flask/__init__.py
entelequia/flask/entelequia.py
entelequia/modules/__init__.py
entelequia/modules/time/__init__.py
entelequia/modules/time/interface.py
entelequia/modules/time/system.py
entelequia/system/__init__.py
entelequia/system/implementation.py
entelequia/system/module.py
entelequia/system/system.py
entelequia/system/system_interface.py
entelequia-0.1.1.dist-info/LICENSE.md
entelequia-0.1.1.dist-info/METADATA
entelequia-0.1.1.dist-info/WHEEL
entelequia-0.1.1.dist-info/RECORD
